jose2ls/__init__.py
jose2ls/cli.py
jose2ls-0.1.0.dist-info/METADATA
jose2ls-0.1.0.dist-info/WHEEL
jose2ls-0.1.0.dist-info/entry_points.txt
jose2ls-0.1.0.dist-info/top_level.txt
jose2ls-0.1.0.dist-info/RECORD
