Metadata-Version: 2.1
Name: jose2ls
Version: 0.1.0
Summary: Add your description here
Requires-Python: >=3.12
Requires-Dist: typer>=0.15.1
